engy/__init__.py
engy/__main__.py
engy/app_builder.py
engy/app_cloner.py
engy/app_split.py
engy/code_map.py
engy/code_map_test.py
engy/llm.py
engy/main.py
engy/produce_files.py
engy/produce_files_test.py
engy/util.py
engy/agents/airbnb_review_agent.py
engy/agents/web_scraper_agent.py
engy/agents/web_search_agent.py
engy-0.0.9.dist-info/LICENSE
engy-0.0.9.dist-info/METADATA
engy-0.0.9.dist-info/WHEEL
engy-0.0.9.dist-info/entry_points.txt
engy-0.0.9.dist-info/top_level.txt
engy-0.0.9.dist-info/RECORD
