Metadata-Version: 2.1
Name: engy
Version: 0.0.9
Summary: Engy is an AI-powered development tool that generates fully functional web applications from natural language, streamlining the process from idea to working prototype.
Author-email: Ning Ren <renning22@gmail.com>
Maintainer-email: Ning Ren <renning22@gmail.com>
Project-URL: Homepage, https://github.com/renning22/engy
Project-URL: Bug Reports, https://github.com/renning22/engy/issues
Project-URL: Funding, https://github.com/renning22/engy
Project-URL: Say Thanks!, https://github.com/renning22/engy
Project-URL: Source, https://github.com/renning22/engy
Keywords: setuptools,development
Classifier: Development Status :: 3 - Alpha
Classifier: Intended Audience :: Developers
Classifier: Topic :: Software Development :: Build Tools
Classifier: License :: OSI Approved :: MIT License
Classifier: Programming Language :: Python :: 3
Classifier: Programming Language :: Python :: 3.7
Classifier: Programming Language :: Python :: 3.8
Classifier: Programming Language :: Python :: 3.9
Classifier: Programming Language :: Python :: 3.10
Classifier: Programming Language :: Python :: 3.11
Classifier: Programming Language :: Python :: 3 :: Only
Requires-Python: >=3.7
License-File: LICENSE
Requires-Dist: anthropic
Requires-Dist: crewai-tools
Requires-Dist: litellm
Requires-Dist: python-dotenv
Provides-Extra: dev
Requires-Dist: check-manifest; extra == "dev"
Provides-Extra: test
Requires-Dist: coverage; extra == "test"
